{"code":200,"status":"OK","data":{"timings":{"Fajr":"05:26","Sunrise":"06:44","Dhuhr":"12:47","Asr":"16:11","Sunset":"18:50","Maghrib":"18:50","Isha":"20:08","Imsak":"05:16","Midnight":"00:47"},"date":{"readable":"23 Sep 2021","timestamp":"1632369606","hijri":{"date":"15-02-1443","format":"DD-MM-YYYY","day":"15","weekday":{"en":"Al Khamees","ar":"\u0627\u0644\u062e\u0645\u064a\u0633"},"month":{"number":2,"en":"\u1e62afar","ar":"\u0635\u064e\u0641\u064e\u0631"},"year":"1443","designation":{"abbreviated":"AH","expanded":"Anno Hegirae"},"holidays":[]},"gregorian":{"date":"23-09-2021","format":"DD-MM-YYYY","day":"23","weekday":{"en":"Thursday"},"month":{"number":9,"en":"September"},"year":"2021","designation":{"abbreviated":"AD","expanded":"Anno Domini"}}},"meta":{"latitude":42.8371299,"longitude":-73.7364146,"timezone":"America\/New_York","method":{"id":2,"name":"Islamic Society of North America (ISNA)","params":{"Fajr":15,"Isha":15},"location":{"latitude":39.70421229999999,"longitude":-86.39943869999999}},"latitudeAdjustmentMethod":"ANGLE_BASED","midnightMode":"STANDARD","school":"STANDARD","offset":{"Imsak":0,"Fajr":0,"Sunrise":0,"Dhuhr":0,"Asr":0,"Maghrib":0,"Sunset":0,"Isha":0,"Midnight":0}}}}